djapm/__init__.py
djapm/apm/__init__.py
djapm/apm/admin.py
djapm/apm/api/__init__.py
djapm/apm/api/views.py
djapm/apm/apps.py
djapm/apm/contrib.py
djapm/apm/decorators.py
djapm/apm/dflt_conf.py
djapm/apm/filters.py
djapm/apm/generics.py
djapm/apm/integrations/__init__.py
djapm/apm/integrations/base.py
djapm/apm/integrations/discord.py
djapm/apm/integrations/slack.py
djapm/apm/locale/pt_BR/LC_MESSAGES/django.po
djapm/apm/locale/pt_BR/LC_MESSAGES/djangojs.po
djapm/apm/log.py
djapm/apm/middlewares.py
djapm/apm/migrations/0001_initial.py
djapm/apm/migrations/0002_apirequest_view_name.py
djapm/apm/migrations/__init__.py
djapm/apm/mixins.py
djapm/apm/models.py
djapm/apm/static/apm/css/dashboard.css
djapm/apm/static/apm/js/chart.js
djapm/apm/static/apm/js/fetch-utils.js
djapm/apm/tasks.py
djapm/apm/templates/admin/app_list.html
djapm/apm/templates/apm/dashboard.html
djapm/apm/types.py
djapm/apm/urls.py
djapm/apm/views.py
djapm/settings.py
django_apm-0.3.0.dist-info/WHEEL
django_apm-0.3.0.dist-info/METADATA
django_apm-0.3.0.dist-info/licenses/LICENSE
django_apm-0.3.0.dist-info/RECORD
