Metadata-Version: 2.1
Name: django-apm
Version: 0.3.0
Summary: A fully featured APM for django using django
License: MIT
Author-email: Leandro de Souza <leandrodesouzadev@gmail.com>
Requires-Python: >=3.9
Requires-Dist: Django>=4.1.1
Requires-Dist: celery>=5.2.7
Requires-Dist: djangorestframework>=3.14.0
Requires-Dist: requests>=2.28.1
Project-URL: Homepage, https://github.com/plathanus-tech/django-apm
Project-URL: download_url, https://github.com/plathanus-tech/django-apm/releases/tag/v0.3.0
